{
  "type": "GROUP",
"name": "Global Information",
"path": "",
"pathFormatted": "group_missing-name-b06d1",
"stats": {
    "name": "Global Information",
    "numberOfRequests": {
        "total": 20391,
        "ok": 20391,
        "ko": 0
    },
    "minResponseTime": {
        "total": 61,
        "ok": 61,
        "ko": 0
    },
    "maxResponseTime": {
        "total": 13147,
        "ok": 13147,
        "ko": 0
    },
    "meanResponseTime": {
        "total": 798,
        "ok": 798,
        "ko": 0
    },
    "standardDeviation": {
        "total": 951,
        "ok": 951,
        "ko": 0
    },
    "percentiles1": {
        "total": 485,
        "ok": 485,
        "ko": 0
    },
    "percentiles2": {
        "total": 987,
        "ok": 987,
        "ko": 0
    },
    "percentiles3": {
        "total": 2608,
        "ok": 2608,
        "ko": 0
    },
    "percentiles4": {
        "total": 4853,
        "ok": 4853,
        "ko": 0
    },
    "group1": {
    "name": "t < 100 ms",
    "count": 1672,
    "percentage": 8
},
    "group2": {
    "name": "100 ms < t < 500 ms",
    "count": 8736,
    "percentage": 43
},
    "group3": {
    "name": "t > 500 ms",
    "count": 9983,
    "percentage": 49
},
    "group4": {
    "name": "failed",
    "count": 0,
    "percentage": 0
},
    "meanNumberOfRequestsPerSecond": {
        "total": 67.97,
        "ok": 67.97,
        "ko": 0
    }
},
"contents": {
"req_auth-check-cebcf": {
        "type": "REQUEST",
        "name": "auth-check",
"path": "auth-check",
"pathFormatted": "req_auth-check-cebcf",
"stats": {
    "name": "auth-check",
    "numberOfRequests": {
        "total": 200,
        "ok": 200,
        "ko": 0
    },
    "minResponseTime": {
        "total": 228,
        "ok": 228,
        "ko": 0
    },
    "maxResponseTime": {
        "total": 1635,
        "ok": 1635,
        "ko": 0
    },
    "meanResponseTime": {
        "total": 355,
        "ok": 355,
        "ko": 0
    },
    "standardDeviation": {
        "total": 224,
        "ok": 224,
        "ko": 0
    },
    "percentiles1": {
        "total": 263,
        "ok": 263,
        "ko": 0
    },
    "percentiles2": {
        "total": 351,
        "ok": 351,
        "ko": 0
    },
    "percentiles3": {
        "total": 821,
        "ok": 821,
        "ko": 0
    },
    "percentiles4": {
        "total": 1422,
        "ok": 1422,
        "ko": 0
    },
    "group1": {
    "name": "t < 100 ms",
    "count": 0,
    "percentage": 0
},
    "group2": {
    "name": "100 ms < t < 500 ms",
    "count": 173,
    "percentage": 87
},
    "group3": {
    "name": "t > 500 ms",
    "count": 27,
    "percentage": 14
},
    "group4": {
    "name": "failed",
    "count": 0,
    "percentage": 0
},
    "meanNumberOfRequestsPerSecond": {
        "total": 0.6666666666666666,
        "ok": 0.6666666666666666,
        "ko": 0
    }
}
    },"req_home-page-fdc40": {
        "type": "REQUEST",
        "name": "home-page",
"path": "home-page",
"pathFormatted": "req_home-page-fdc40",
"stats": {
    "name": "home-page",
    "numberOfRequests": {
        "total": 1268,
        "ok": 1268,
        "ko": 0
    },
    "minResponseTime": {
        "total": 87,
        "ok": 87,
        "ko": 0
    },
    "maxResponseTime": {
        "total": 4676,
        "ok": 4676,
        "ko": 0
    },
    "meanResponseTime": {
        "total": 526,
        "ok": 526,
        "ko": 0
    },
    "standardDeviation": {
        "total": 542,
        "ok": 542,
        "ko": 0
    },
    "percentiles1": {
        "total": 318,
        "ok": 318,
        "ko": 0
    },
    "percentiles2": {
        "total": 596,
        "ok": 596,
        "ko": 0
    },
    "percentiles3": {
        "total": 1658,
        "ok": 1658,
        "ko": 0
    },
    "percentiles4": {
        "total": 2741,
        "ok": 2741,
        "ko": 0
    },
    "group1": {
    "name": "t < 100 ms",
    "count": 12,
    "percentage": 1
},
    "group2": {
    "name": "100 ms < t < 500 ms",
    "count": 861,
    "percentage": 68
},
    "group3": {
    "name": "t > 500 ms",
    "count": 395,
    "percentage": 31
},
    "group4": {
    "name": "failed",
    "count": 0,
    "percentage": 0
},
    "meanNumberOfRequestsPerSecond": {
        "total": 4.226666666666667,
        "ok": 4.226666666666667,
        "ko": 0
    }
}
    },"req_fti-default-png-26fa6": {
        "type": "REQUEST",
        "name": "fti-default.png",
"path": "fti-default.png",
"pathFormatted": "req_fti-default-png-26fa6",
"stats": {
    "name": "fti-default.png",
    "numberOfRequests": {
        "total": 200,
        "ok": 200,
        "ko": 0
    },
    "minResponseTime": {
        "total": 68,
        "ok": 68,
        "ko": 0
    },
    "maxResponseTime": {
        "total": 1692,
        "ok": 1692,
        "ko": 0
    },
    "meanResponseTime": {
        "total": 165,
        "ok": 165,
        "ko": 0
    },
    "standardDeviation": {
        "total": 188,
        "ok": 188,
        "ko": 0
    },
    "percentiles1": {
        "total": 84,
        "ok": 84,
        "ko": 0
    },
    "percentiles2": {
        "total": 175,
        "ok": 175,
        "ko": 0
    },
    "percentiles3": {
        "total": 486,
        "ok": 486,
        "ko": 0
    },
    "percentiles4": {
        "total": 863,
        "ok": 863,
        "ko": 0
    },
    "group1": {
    "name": "t < 100 ms",
    "count": 117,
    "percentage": 59
},
    "group2": {
    "name": "100 ms < t < 500 ms",
    "count": 73,
    "percentage": 37
},
    "group3": {
    "name": "t > 500 ms",
    "count": 10,
    "percentage": 5
},
    "group4": {
    "name": "failed",
    "count": 0,
    "percentage": 0
},
    "meanNumberOfRequestsPerSecond": {
        "total": 0.6666666666666666,
        "ok": 0.6666666666666666,
        "ko": 0
    }
}
    },"req_view-contexts-01bdc": {
        "type": "REQUEST",
        "name": "view-contexts",
"path": "view-contexts",
"pathFormatted": "req_view-contexts-01bdc",
"stats": {
    "name": "view-contexts",
    "numberOfRequests": {
        "total": 1196,
        "ok": 1196,
        "ko": 0
    },
    "minResponseTime": {
        "total": 61,
        "ok": 61,
        "ko": 0
    },
    "maxResponseTime": {
        "total": 6062,
        "ok": 6062,
        "ko": 0
    },
    "meanResponseTime": {
        "total": 453,
        "ok": 453,
        "ko": 0
    },
    "standardDeviation": {
        "total": 668,
        "ok": 668,
        "ko": 0
    },
    "percentiles1": {
        "total": 218,
        "ok": 218,
        "ko": 0
    },
    "percentiles2": {
        "total": 503,
        "ok": 503,
        "ko": 0
    },
    "percentiles3": {
        "total": 1684,
        "ok": 1684,
        "ko": 0
    },
    "percentiles4": {
        "total": 3271,
        "ok": 3271,
        "ko": 0
    },
    "group1": {
    "name": "t < 100 ms",
    "count": 398,
    "percentage": 33
},
    "group2": {
    "name": "100 ms < t < 500 ms",
    "count": 496,
    "percentage": 41
},
    "group3": {
    "name": "t > 500 ms",
    "count": 302,
    "percentage": 25
},
    "group4": {
    "name": "failed",
    "count": 0,
    "percentage": 0
},
    "meanNumberOfRequestsPerSecond": {
        "total": 3.986666666666667,
        "ok": 3.986666666666667,
        "ko": 0
    }
}
    },"req_users-9bc65": {
        "type": "REQUEST",
        "name": "users",
"path": "users",
"pathFormatted": "req_users-9bc65",
"stats": {
    "name": "users",
    "numberOfRequests": {
        "total": 1196,
        "ok": 1196,
        "ko": 0
    },
    "minResponseTime": {
        "total": 61,
        "ok": 61,
        "ko": 0
    },
    "maxResponseTime": {
        "total": 6777,
        "ok": 6777,
        "ko": 0
    },
    "meanResponseTime": {
        "total": 422,
        "ok": 422,
        "ko": 0
    },
    "standardDeviation": {
        "total": 632,
        "ok": 632,
        "ko": 0
    },
    "percentiles1": {
        "total": 218,
        "ok": 218,
        "ko": 0
    },
    "percentiles2": {
        "total": 488,
        "ok": 488,
        "ko": 0
    },
    "percentiles3": {
        "total": 1464,
        "ok": 1464,
        "ko": 0
    },
    "percentiles4": {
        "total": 3154,
        "ok": 3154,
        "ko": 0
    },
    "group1": {
    "name": "t < 100 ms",
    "count": 448,
    "percentage": 37
},
    "group2": {
    "name": "100 ms < t < 500 ms",
    "count": 458,
    "percentage": 38
},
    "group3": {
    "name": "t > 500 ms",
    "count": 290,
    "percentage": 24
},
    "group4": {
    "name": "failed",
    "count": 0,
    "percentage": 0
},
    "meanNumberOfRequestsPerSecond": {
        "total": 3.986666666666667,
        "ok": 3.986666666666667,
        "ko": 0
    }
}
    },"req_search-random-t-3b57c": {
        "type": "REQUEST",
        "name": "search-random-trip",
"path": "search-random-trip",
"pathFormatted": "req_search-random-t-3b57c",
"stats": {
    "name": "search-random-trip",
    "numberOfRequests": {
        "total": 3548,
        "ok": 3548,
        "ko": 0
    },
    "minResponseTime": {
        "total": 63,
        "ok": 63,
        "ko": 0
    },
    "maxResponseTime": {
        "total": 13147,
        "ok": 13147,
        "ko": 0
    },
    "meanResponseTime": {
        "total": 1167,
        "ok": 1167,
        "ko": 0
    },
    "standardDeviation": {
        "total": 1380,
        "ok": 1380,
        "ko": 0
    },
    "percentiles1": {
        "total": 717,
        "ok": 717,
        "ko": 0
    },
    "percentiles2": {
        "total": 1449,
        "ok": 1449,
        "ko": 0
    },
    "percentiles3": {
        "total": 3988,
        "ok": 3988,
        "ko": 0
    },
    "percentiles4": {
        "total": 6789,
        "ok": 6789,
        "ko": 0
    },
    "group1": {
    "name": "t < 100 ms",
    "count": 416,
    "percentage": 12
},
    "group2": {
    "name": "100 ms < t < 500 ms",
    "count": 960,
    "percentage": 27
},
    "group3": {
    "name": "t > 500 ms",
    "count": 2172,
    "percentage": 61
},
    "group4": {
    "name": "failed",
    "count": 0,
    "percentage": 0
},
    "meanNumberOfRequestsPerSecond": {
        "total": 11.826666666666666,
        "ok": 11.826666666666666,
        "ko": 0
    }
}
    },"req_filters-country-e0472": {
        "type": "REQUEST",
        "name": "filters/country-code",
"path": "filters/country-code",
"pathFormatted": "req_filters-country-e0472",
"stats": {
    "name": "filters/country-code",
    "numberOfRequests": {
        "total": 3507,
        "ok": 3507,
        "ko": 0
    },
    "minResponseTime": {
        "total": 89,
        "ok": 89,
        "ko": 0
    },
    "maxResponseTime": {
        "total": 8172,
        "ok": 8172,
        "ko": 0
    },
    "meanResponseTime": {
        "total": 921,
        "ok": 921,
        "ko": 0
    },
    "standardDeviation": {
        "total": 972,
        "ok": 972,
        "ko": 0
    },
    "percentiles1": {
        "total": 598,
        "ok": 598,
        "ko": 0
    },
    "percentiles2": {
        "total": 1161,
        "ok": 1161,
        "ko": 0
    },
    "percentiles3": {
        "total": 2833,
        "ok": 2833,
        "ko": 0
    },
    "percentiles4": {
        "total": 5133,
        "ok": 5133,
        "ko": 0
    },
    "group1": {
    "name": "t < 100 ms",
    "count": 41,
    "percentage": 1
},
    "group2": {
    "name": "100 ms < t < 500 ms",
    "count": 1436,
    "percentage": 41
},
    "group3": {
    "name": "t > 500 ms",
    "count": 2030,
    "percentage": 58
},
    "group4": {
    "name": "failed",
    "count": 0,
    "percentage": 0
},
    "meanNumberOfRequestsPerSecond": {
        "total": 11.69,
        "ok": 11.69,
        "ko": 0
    }
}
    },"req_filters-start-a-a8e8c": {
        "type": "REQUEST",
        "name": "filters/start-airport",
"path": "filters/start-airport",
"pathFormatted": "req_filters-start-a-a8e8c",
"stats": {
    "name": "filters/start-airport",
    "numberOfRequests": {
        "total": 3508,
        "ok": 3508,
        "ko": 0
    },
    "minResponseTime": {
        "total": 100,
        "ok": 100,
        "ko": 0
    },
    "maxResponseTime": {
        "total": 7668,
        "ok": 7668,
        "ko": 0
    },
    "meanResponseTime": {
        "total": 809,
        "ok": 809,
        "ko": 0
    },
    "standardDeviation": {
        "total": 769,
        "ok": 769,
        "ko": 0
    },
    "percentiles1": {
        "total": 579,
        "ok": 579,
        "ko": 0
    },
    "percentiles2": {
        "total": 1022,
        "ok": 1022,
        "ko": 0
    },
    "percentiles3": {
        "total": 2352,
        "ok": 2352,
        "ko": 0
    },
    "percentiles4": {
        "total": 3788,
        "ok": 3788,
        "ko": 0
    },
    "group1": {
    "name": "t < 100 ms",
    "count": 0,
    "percentage": 0
},
    "group2": {
    "name": "100 ms < t < 500 ms",
    "count": 1539,
    "percentage": 44
},
    "group3": {
    "name": "t > 500 ms",
    "count": 1969,
    "percentage": 56
},
    "group4": {
    "name": "failed",
    "count": 0,
    "percentage": 0
},
    "meanNumberOfRequestsPerSecond": {
        "total": 11.693333333333333,
        "ok": 11.693333333333333,
        "ko": 0
    }
}
    },"req_filters-end-air-c74ee": {
        "type": "REQUEST",
        "name": "filters/end-airport",
"path": "filters/end-airport",
"pathFormatted": "req_filters-end-air-c74ee",
"stats": {
    "name": "filters/end-airport",
    "numberOfRequests": {
        "total": 3508,
        "ok": 3508,
        "ko": 0
    },
    "minResponseTime": {
        "total": 100,
        "ok": 100,
        "ko": 0
    },
    "maxResponseTime": {
        "total": 7082,
        "ok": 7082,
        "ko": 0
    },
    "meanResponseTime": {
        "total": 811,
        "ok": 811,
        "ko": 0
    },
    "standardDeviation": {
        "total": 815,
        "ok": 815,
        "ko": 0
    },
    "percentiles1": {
        "total": 563,
        "ok": 563,
        "ko": 0
    },
    "percentiles2": {
        "total": 995,
        "ok": 995,
        "ko": 0
    },
    "percentiles3": {
        "total": 2444,
        "ok": 2444,
        "ko": 0
    },
    "percentiles4": {
        "total": 4326,
        "ok": 4326,
        "ko": 0
    },
    "group1": {
    "name": "t < 100 ms",
    "count": 0,
    "percentage": 0
},
    "group2": {
    "name": "100 ms < t < 500 ms",
    "count": 1565,
    "percentage": 45
},
    "group3": {
    "name": "t > 500 ms",
    "count": 1943,
    "percentage": 55
},
    "group4": {
    "name": "failed",
    "count": 0,
    "percentage": 0
},
    "meanNumberOfRequestsPerSecond": {
        "total": 11.693333333333333,
        "ok": 11.693333333333333,
        "ko": 0
    }
}
    },"req_open-random-tem-8d868": {
        "type": "REQUEST",
        "name": "open-random-template",
"path": "open-random-template",
"pathFormatted": "req_open-random-tem-8d868",
"stats": {
    "name": "open-random-template",
    "numberOfRequests": {
        "total": 1130,
        "ok": 1130,
        "ko": 0
    },
    "minResponseTime": {
        "total": 83,
        "ok": 83,
        "ko": 0
    },
    "maxResponseTime": {
        "total": 5048,
        "ok": 5048,
        "ko": 0
    },
    "meanResponseTime": {
        "total": 498,
        "ok": 498,
        "ko": 0
    },
    "standardDeviation": {
        "total": 493,
        "ok": 493,
        "ko": 0
    },
    "percentiles1": {
        "total": 327,
        "ok": 327,
        "ko": 0
    },
    "percentiles2": {
        "total": 614,
        "ok": 614,
        "ko": 0
    },
    "percentiles3": {
        "total": 1466,
        "ok": 1466,
        "ko": 0
    },
    "percentiles4": {
        "total": 2463,
        "ok": 2463,
        "ko": 0
    },
    "group1": {
    "name": "t < 100 ms",
    "count": 32,
    "percentage": 3
},
    "group2": {
    "name": "100 ms < t < 500 ms",
    "count": 729,
    "percentage": 65
},
    "group3": {
    "name": "t > 500 ms",
    "count": 369,
    "percentage": 33
},
    "group4": {
    "name": "failed",
    "count": 0,
    "percentage": 0
},
    "meanNumberOfRequestsPerSecond": {
        "total": 3.7666666666666666,
        "ok": 3.7666666666666666,
        "ko": 0
    }
}
    },"req_open-random-tem-6f505": {
        "type": "REQUEST",
        "name": "open-random-template-ajax",
"path": "open-random-template-ajax",
"pathFormatted": "req_open-random-tem-6f505",
"stats": {
    "name": "open-random-template-ajax",
    "numberOfRequests": {
        "total": 1130,
        "ok": 1130,
        "ko": 0
    },
    "minResponseTime": {
        "total": 67,
        "ok": 67,
        "ko": 0
    },
    "maxResponseTime": {
        "total": 8683,
        "ok": 8683,
        "ko": 0
    },
    "meanResponseTime": {
        "total": 738,
        "ok": 738,
        "ko": 0
    },
    "standardDeviation": {
        "total": 999,
        "ok": 999,
        "ko": 0
    },
    "percentiles1": {
        "total": 384,
        "ok": 384,
        "ko": 0
    },
    "percentiles2": {
        "total": 963,
        "ok": 963,
        "ko": 0
    },
    "percentiles3": {
        "total": 2345,
        "ok": 2345,
        "ko": 0
    },
    "percentiles4": {
        "total": 4872,
        "ok": 4872,
        "ko": 0
    },
    "group1": {
    "name": "t < 100 ms",
    "count": 208,
    "percentage": 18
},
    "group2": {
    "name": "100 ms < t < 500 ms",
    "count": 446,
    "percentage": 39
},
    "group3": {
    "name": "t > 500 ms",
    "count": 476,
    "percentage": 42
},
    "group4": {
    "name": "failed",
    "count": 0,
    "percentage": 0
},
    "meanNumberOfRequestsPerSecond": {
        "total": 3.7666666666666666,
        "ok": 3.7666666666666666,
        "ko": 0
    }
}
    }
}

}